splatbot/__init__.py
splatbot/cli.py
splatbot/controller.py
splatbot/macro.py
splatbot/simulation.py
splatbot/start.py
splatbot-1.1.0.dist-info/METADATA
splatbot-1.1.0.dist-info/WHEEL
splatbot-1.1.0.dist-info/entry_points.txt
splatbot-1.1.0.dist-info/licenses/LICENSE
splatbot-1.1.0.dist-info/RECORD
