Metadata-Version: 2.4
Name: splatbot
Version: 1.1.0
Summary: Automate plotting posts in Splatoon based on BlueZ, and optimize its efficiency via Traveling Salesman Problem (TSP).
Project-URL: Changelog, https://github.com/necusjz/splatbot/blob/main/CHANGELOG.md
Project-URL: Repository, https://github.com/necusjz/splatbot
Author-email: necusjz <necusjz@gmail.com>
License-File: LICENSE
Classifier: Development Status :: 5 - Production/Stable
Classifier: Intended Audience :: Science/Research
Classifier: License :: OSI Approved :: MIT License
Classifier: Programming Language :: Python
Classifier: Topic :: Scientific/Engineering :: Artificial Intelligence
Requires-Python: <3.12,>=3.9
Requires-Dist: click>=8.1.3
Requires-Dist: matplotlib>=3.6.3
Requires-Dist: numpy>=1.23.2
Requires-Dist: nxbt>=0.1.4
Requires-Dist: pillow>=9.2.0
Requires-Dist: scipy>=1.9.1
Requires-Dist: tqdm>=4.64.0
Requires-Dist: tsp-solver2>=0.4.1
Provides-Extra: dev
Requires-Dist: build<2.0.0,>=1.0.3; extra == 'dev'
Requires-Dist: isort>=5.6.4; extra == 'dev'
Requires-Dist: packaging>=23.1; extra == 'dev'
Requires-Dist: pytest>=7.2.1; extra == 'dev'
Requires-Dist: ruff>=0.1.2; extra == 'dev'
Requires-Dist: tabulate>=0.9.0; extra == 'dev'
Requires-Dist: twine>=5.1.1; extra == 'dev'
